scripts/__init__.py
scripts/athlete_controller.py
scripts/base.py
scripts/race_controller.py
spartaORM/__init__.py
spartaORM/controller/__init__.py
spartaORM/controller/athlete.py
spartaORM/controller/averages.py
spartaORM/controller/base.py
spartaORM/controller/official_results.py
spartaORM/controller/pacing.py
spartaORM/controller/race.py
spartaORM/controller/segment_metrics.py
spartaORM/controller/summary_metrics.py
spartaORM/enums/__init__.py
spartaORM/enums/sex.py
spartaORM/enums/swim.py
spartaORM/models/__init__.py
spartaORM/models/athlete.py
spartaORM/models/averages.py
spartaORM/models/base.py
spartaORM/models/official_results.py
spartaORM/models/pacing.py
spartaORM/models/race.py
spartaORM/models/segment_metrics.py
spartaORM/models/summary_metrics.py
spartaORM/utils/__init__.py
spartaORM/utils/boolean.py
spartaORM/utils/boolean_test.py
spartaORM/utils/date.py
spartaORM/utils/date_test.py
spartaORM/utils/enums.py
spartaORM/utils/enums_test.py
spartaORM-0.1.4.dist-info/LICENSE.txt
spartaORM-0.1.4.dist-info/METADATA
spartaORM-0.1.4.dist-info/WHEEL
spartaORM-0.1.4.dist-info/top_level.txt
spartaORM-0.1.4.dist-info/RECORD
