Metadata-Version: 2.1
Name: spartaORM
Version: 0.1.4
Summary: Simple ORM for Sparta
Home-page: https://gitlab.com/arun-ak/sparta-database-orm
Author: Arun Kumar
Author-email: arun.kumar@swimming.org.au
License: MIT
Platform: UNKNOWN
Classifier: Topic :: Software Development :: Build Tools
License-File: LICENSE.txt
Requires-Dist: alembic
Requires-Dist: sqlalchemy
Requires-Dist: psycopg2
